yclients_aio_client/__init__.py
yclients_aio_client/__version__.py
yclients_aio_client/_typing.py
yclients_aio_client/base.py
yclients_aio_client/constants.py
yclients_aio_client/exceptions.py
yclients_aio_client-0.0.1.dist-info/AUTHORS
yclients_aio_client-0.0.1.dist-info/LICENSE
yclients_aio_client-0.0.1.dist-info/METADATA
yclients_aio_client-0.0.1.dist-info/WHEEL
yclients_aio_client-0.0.1.dist-info/top_level.txt
yclients_aio_client-0.0.1.dist-info/RECORD
