Metadata-Version: 2.1
Name: yclients-aio-client
Version: 0.0.1
Summary: Async client for YCLIENTS API
Home-page: https://github.com/akimrx/yclients-aio-client
Author: akimrx
Author-email: akimstrong@yandex.ru
License: MIT
Keywords: yclients,async
Platform: osx
Platform: linux
Platform: windows
Classifier: Intended Audience :: Developers
Classifier: Programming Language :: Python :: 3.10
Classifier: Operating System :: Unix
Classifier: Operating System :: MacOS :: MacOS X
Classifier: Operating System :: Microsoft :: Windows
Requires-Python: >=3.10
License-File: LICENSE
License-File: AUTHORS
Requires-Dist: aiohttp ==3.8.*
Requires-Dist: async-timeout ==4.*
Requires-Dist: pydantic ==2.4.*
Requires-Dist: pydantic-settings ==2.*
